easyopenchat/__init__.py
easyopenchat/chatbot.py
easyopenchat/cli.py
easyopenchat/client.py
easyopenchat/gui.py
easyopenchat/memory.py
easyopenchat/prompts.py
easyopenchat/vector_memory.py
easyopenchat/web.py
easyopenchat/plugins/__init__.py
easyopenchat/plugins/calc_plugin.py
easyopenchat/plugins/plugin_loader.py
easyopenchat/plugins/time_plugin.py
easyopenchat-0.3.0.dist-info/METADATA
easyopenchat-0.3.0.dist-info/WHEEL
easyopenchat-0.3.0.dist-info/top_level.txt
easyopenchat-0.3.0.dist-info/RECORD
