Metadata-Version: 2.4
Name: easyopenchat
Version: 0.3.0
Summary: An easy, beginner-friendly chatbot SDK powered by OpenRouter
Author-email: Sriram G <sriramkrish379@gmail.com>
License: MIT
Keywords: chatbot,openai,openrouter,gradio,api,bot
Requires-Python: >=3.8
Requires-Dist: requests>=2.28.0
Requires-Dist: jinja2>=3.1.0
Requires-Dist: gradio>=4.44.1
Requires-Dist: fastapi>=0.100.0
Requires-Dist: uvicorn>=0.23.0
Requires-Dist: rich>=13.0.0
Provides-Extra: vector
Requires-Dist: faiss-cpu>=1.7.0; extra == "vector"
Requires-Dist: numpy>=1.21.0; extra == "vector"
